{
  "b": 155,
  "disableInputWhenNotFocused": true,
  "mangledName": "Main_32Scene",
  "name": "Main Scene",
  "r": 155,
  "standardSortMethod": true,
  "stopSoundsOnStartup": true,
  "title": "",
  "v": 155,
  "uiSettings": {
    "grid": true,
    "gridType": "rectangular",
    "gridWidth": 32,
    "gridHeight": 32,
    "gridDepth": 32,
    "gridOffsetX": 0,
    "gridOffsetY": 0,
    "gridOffsetZ": 0,
    "gridColor": 10401023,
    "gridAlpha": 0.8,
    "snap": true,
    "zoomFactor": 0.7876290101674168,
    "windowMask": false,
    "selectedLayer": "",
    "gameEditorMode": "instances-editor"
  },
  "objectsGroups": [
    {
      "name": "all",
      "objects": [
        {
          "name": "DontForget"
        },
        {
          "name": "stamina_background"
        },
        {
          "name": "Dialogue"
        },
        {
          "name": "options"
        },
        {
          "name": "black_backdrop"
        },
        {
          "name": "butch"
        },
        {
          "name": "secret_butch"
        },
        {
          "name": "sky"
        },
        {
          "name": "cloud_"
        },
        {
          "name": "butch_house_"
        },
        {
          "name": "aaron"
        },
        {
          "name": "TreeSprite1"
        },
        {
          "name": "GreenTree"
        },
        {
          "name": "BoundarySprite"
        },
        {
          "name": "NewText"
        },
        {
          "name": "BlackDecoratedButton"
        },
        {
          "name": "stamina_bar"
        },
        {
          "name": "test"
        },
        {
          "name": "Oliver_Player"
        },
        {
          "name": "path"
        },
        {
          "name": "grass"
        },
        {
          "name": "TreeObject1"
        },
        {
          "name": "SSD"
        },
        {
          "name": "RockObject"
        }
      ]
    }
  ],
  "variables": [
    {
      "name": "interacting_true",
      "type": "number",
      "value": 0
    },
    {
      "name": "dashing_true",
      "type": "string",
      "value": "no"
    },
    {
      "name": "stamina",
      "type": "number",
      "value": 100
    },
    {
      "name": "stamina_var",
      "type": "number",
      "value": 0
    },
    {
      "name": "textscrollspeed",
      "type": "number",
      "value": 0
    }
  ],
  "instances": [],
  "objects": [
    {
      "assetStoreId": "",
      "bold": false,
      "italic": false,
      "name": "DontForget",
      "smoothed": true,
      "type": "TextObject::Text",
      "underlined": false,
      "variables": [],
      "effects": [],
      "behaviors": [],
      "string": "DON'T FORGET:\n1. Use external events\n2. Only 1 person works on each file at a time (events, scenes, etc)\n3. Name objects and assets (No NewSprite)\n4. Commit often",
      "font": "",
      "textAlignment": "left",
      "characterSize": 48,
      "color": {
        "b": 0,
        "g": 0,
        "r": 0
      },
      "content": {
        "bold": false,
        "isOutlineEnabled": false,
        "isShadowEnabled": false,
        "italic": false,
        "outlineColor": "255;255;255",
        "outlineThickness": 2,
        "shadowAngle": 90,
        "shadowBlurRadius": 2,
        "shadowColor": "0;0;0",
        "shadowDistance": 4,
        "shadowOpacity": 127,
        "smoothed": true,
        "underlined": false,
        "text": "DON'T FORGET:\n1. Use external events\n2. Only 1 person works on each file at a time (events, scenes, etc)\n3. Name objects and assets (No NewSprite)\n4. Commit often",
        "font": "",
        "textAlignment": "left",
        "verticalTextAlignment": "top",
        "characterSize": 48,
        "lineHeight": 0,
        "color": "0;0;0"
      }
    },
    {
      "adaptCollisionMaskAutomatically": true,
      "assetStoreId": "",
      "name": "SSD",
      "type": "Sprite",
      "updateIfNotVisible": false,
      "variables": [],
      "effects": [],
      "behaviors": [],
      "animations": [
        {
          "name": "NewSprite",
          "useMultipleDirections": false,
          "directions": [
            {
              "looping": false,
              "metadata": "{\"pskl\":{}}",
              "timeBetweenFrames": 0.08,
              "sprites": [
                {
                  "hasCustomCollisionMask": true,
                  "image": "SSD",
                  "points": [],
                  "originPoint": {
                    "name": "origine",
                    "x": 0,
                    "y": 0
                  },
                  "centerPoint": {
                    "automatic": true,
                    "name": "centre",
                    "x": 0,
                    "y": 0
                  },
                  "customCollisionMask": [
                    [
                      {
                        "x": 7,
                        "y": 12
                      },
                      {
                        "x": 49,
                        "y": 12
                      },
                      {
                        "x": 49,
                        "y": 49
                      },
                      {
                        "x": 7,
                        "y": 49
                      }
                    ]
                  ]
                }
              ]
            }
          ]
        }
      ]
    },
    {
      "adaptCollisionMaskAutomatically": true,
      "assetStoreId": "",
      "name": "RockObject",
      "persistentUuid": "3bf03e98-3e91-44a6-b7ca-2993fcd5efa5",
      "type": "Sprite",
      "updateIfNotVisible": false,
      "variables": [],
      "effects": [],
      "behaviors": [],
      "animations": [
        {
          "name": "AmbientObjectsPilgrim2",
          "useMultipleDirections": false,
          "directions": [
            {
              "looping": false,
              "metadata": "{\"pskl\":{}}",
              "timeBetweenFrames": 0.08,
              "sprites": [
                {
                  "hasCustomCollisionMask": true,
                  "image": "AmbientObjectsPilgrim2",
                  "points": [],
                  "originPoint": {
                    "name": "origine",
                    "x": 0,
                    "y": 0
                  },
                  "centerPoint": {
                    "automatic": true,
                    "name": "centre",
                    "x": 0,
                    "y": 0
                  },
                  "customCollisionMask": [
                    [
                      {
                        "x": 0,
                        "y": 0
                      },
                      {
                        "x": 16,
                        "y": 0
                      },
                      {
                        "x": 16,
                        "y": 8
                      },
                      {
                        "x": 0,
                        "y": 8
                      }
                    ]
                  ]
                }
              ]
            }
          ]
        }
      ]
    },
    {
      "adaptCollisionMaskAutomatically": true,
      "assetStoreId": "",
      "name": "TreeObject1",
      "type": "Sprite",
      "updateIfNotVisible": false,
      "variables": [],
      "effects": [],
      "behaviors": [],
      "animations": [
        {
          "name": "",
          "useMultipleDirections": false,
          "directions": [
            {
              "looping": false,
              "timeBetweenFrames": 0.08,
              "sprites": [
                {
                  "hasCustomCollisionMask": true,
                  "image": "TreeObject2.png",
                  "points": [],
                  "originPoint": {
                    "name": "origine",
                    "x": 0,
                    "y": 0
                  },
                  "centerPoint": {
                    "automatic": true,
                    "name": "centre",
                    "x": 0,
                    "y": 0
                  },
                  "customCollisionMask": [
                    [
                      {
                        "x": 6,
                        "y": 10
                      },
                      {
                        "x": 228,
                        "y": 10
                      },
                      {
                        "x": 228,
                        "y": 267
                      },
                      {
                        "x": 6,
                        "y": 267
                      }
                    ]
                  ]
                }
              ]
            }
          ]
        }
      ]
    },
    {
      "assetStoreId": "",
      "height": 32,
      "name": "grass",
      "persistentUuid": "0184dc85-1ea0-404f-8098-e89637afc19a",
      "texture": "NewTiledSprite",
      "type": "TiledSpriteObject::TiledSprite",
      "width": 32,
      "variables": [],
      "effects": [],
      "behaviors": []
    },
    {
      "assetStoreId": "",
      "height": 32,
      "name": "path",
      "persistentUuid": "7bfdb333-52f0-42bf-8894-a4c390c9a6ce",
      "texture": "NewTiledSprite2",
      "type": "TiledSpriteObject::TiledSprite",
      "width": 32,
      "variables": [],
      "effects": [],
      "behaviors": []
    },
    {
      "adaptCollisionMaskAutomatically": true,
      "assetStoreId": "",
      "name": "Oliver_Player",
      "type": "Sprite",
      "updateIfNotVisible": false,
      "variables": [],
      "effects": [],
      "behaviors": [
        {
          "name": "TopDownMovement",
          "type": "TopDownMovementBehavior::TopDownMovementBehavior",
          "acceleration": 10000,
          "allowDiagonals": true,
          "angleOffset": 0,
          "angularMaxSpeed": 180,
          "customIsometryAngle": 30,
          "deceleration": 10000,
          "ignoreDefaultControls": false,
          "maxSpeed": 300,
          "movementAngleOffset": 0,
          "rotateObject": false,
          "useLegacyTurnBack": false,
          "viewpoint": "TopDown"
        }
      ],
      "animations": [
        {
          "name": "WalkingUpwards",
          "useMultipleDirections": false,
          "directions": [
            {
              "looping": false,
              "metadata": "{\"pskl\":{}}",
              "timeBetweenFrames": 0.08,
              "sprites": [
                {
                  "hasCustomCollisionMask": true,
                  "image": "pxArt (4)-sheett",
                  "points": [],
                  "originPoint": {
                    "name": "origine",
                    "x": 0,
                    "y": 0
                  },
                  "centerPoint": {
                    "automatic": true,
                    "name": "centre",
                    "x": 0,
                    "y": 0
                  },
                  "customCollisionMask": [
                    [
                      {
                        "x": 0,
                        "y": 0
                      },
                      {
                        "x": 93,
                        "y": 0
                      },
                      {
                        "x": 93,
                        "y": 104
                      },
                      {
                        "x": 0,
                        "y": 104
                      }
                    ]
                  ]
                }
              ]
            }
          ]
        },
        {
          "name": "WalkingLeft",
          "useMultipleDirections": false,
          "directions": [
            {
              "looping": false,
              "metadata": "{\"pskl\":{}}",
              "timeBetweenFrames": 0.08,
              "sprites": [
                {
                  "hasCustomCollisionMask": true,
                  "image": "WalkingLeft",
                  "points": [],
                  "originPoint": {
                    "name": "origine",
                    "x": 0,
                    "y": 0
                  },
                  "centerPoint": {
                    "automatic": true,
                    "name": "centre",
                    "x": 0,
                    "y": 0
                  },
                  "customCollisionMask": [
                    [
                      {
                        "x": 0,
                        "y": 0
                      },
                      {
                        "x": 93,
                        "y": 0
                      },
                      {
                        "x": 93,
                        "y": 104
                      },
                      {
                        "x": 0,
                        "y": 104
                      }
                    ]
                  ]
                }
              ]
            }
          ]
        },
        {
          "name": "WalkingRight",
          "useMultipleDirections": false,
          "directions": [
            {
              "looping": false,
              "metadata": "{\"pskl\":{}}",
              "timeBetweenFrames": 0.08,
              "sprites": [
                {
                  "hasCustomCollisionMask": true,
                  "image": "WalkingRight",
                  "points": [],
                  "originPoint": {
                    "name": "origine",
                    "x": 0,
                    "y": 0
                  },
                  "centerPoint": {
                    "automatic": true,
                    "name": "centre",
                    "x": 0,
                    "y": 0
                  },
                  "customCollisionMask": [
                    [
                      {
                        "x": 0,
                        "y": 0
                      },
                      {
                        "x": 93,
                        "y": 0
                      },
                      {
                        "x": 93,
                        "y": 104
                      },
                      {
                        "x": 0,
                        "y": 104
                      }
                    ]
                  ]
                }
              ]
            }
          ]
        },
        {
          "name": "WalkingDownwards",
          "useMultipleDirections": false,
          "directions": [
            {
              "looping": false,
              "metadata": "{\"pskl\":{}}",
              "timeBetweenFrames": 0.08,
              "sprites": [
                {
                  "hasCustomCollisionMask": true,
                  "image": "WalkingBackwards",
                  "points": [],
                  "originPoint": {
                    "name": "origine",
                    "x": 0,
                    "y": 0
                  },
                  "centerPoint": {
                    "automatic": true,
                    "name": "centre",
                    "x": 0,
                    "y": 0
                  },
                  "customCollisionMask": [
                    [
                      {
                        "x": 0,
                        "y": 0
                      },
                      {
                        "x": 93,
                        "y": 0
                      },
                      {
                        "x": 93,
                        "y": 104
                      },
                      {
                        "x": 0,
                        "y": 104
                      }
                    ]
                  ]
                }
              ]
            }
          ]
        }
      ]
    },
    {
      "assetStoreId": "",
      "bold": false,
      "italic": false,
      "name": "test",
      "smoothed": true,
      "type": "TextObject::Text",
      "underlined": false,
      "variables": [],
      "effects": [],
      "behaviors": [],
      "string": "f",
      "font": "",
      "textAlignment": "left",
      "characterSize": 20,
      "color": {
        "b": 0,
        "g": 0,
        "r": 0
      },
      "content": {
        "bold": false,
        "isOutlineEnabled": false,
        "isShadowEnabled": false,
        "italic": false,
        "outlineColor": "255;255;255",
        "outlineThickness": 2,
        "shadowAngle": 90,
        "shadowBlurRadius": 2,
        "shadowColor": "0;0;0",
        "shadowDistance": 4,
        "shadowOpacity": 127,
        "smoothed": true,
        "underlined": false,
        "text": "f",
        "font": "",
        "textAlignment": "left",
        "verticalTextAlignment": "top",
        "characterSize": 20,
        "lineHeight": 0,
        "color": "0;0;0"
      }
    },
    {
      "assetStoreId": "",
      "name": "stamina_bar",
      "persistentUuid": "ab072f03-fdea-40ce-8f5b-9140f32d59b5",
      "type": "PrimitiveDrawing::Drawer",
      "variables": [],
      "effects": [],
      "behaviors": [],
      "fillOpacity": 255,
      "outlineSize": 1,
      "outlineOpacity": 255,
      "absoluteCoordinates": true,
      "clearBetweenFrames": true,
      "antialiasing": "none",
      "fillColor": {
        "r": 255,
        "g": 0,
        "b": 0
      },
      "outlineColor": {
        "r": 255,
        "g": 0,
        "b": 0
      }
    },
    {
      "assetStoreId": "",
      "name": "stamina_background",
      "type": "PrimitiveDrawing::Drawer",
      "variables": [],
      "effects": [],
      "behaviors": [],
      "fillOpacity": 255,
      "outlineSize": 1,
      "outlineOpacity": 255,
      "absoluteCoordinates": true,
      "clearBetweenFrames": true,
      "antialiasing": "none",
      "fillColor": {
        "r": 156,
        "g": 147,
        "b": 147
      },
      "outlineColor": {
        "r": 156,
        "g": 147,
        "b": 147
      }
    },
    {
      "assetStoreId": "",
      "bold": true,
      "italic": false,
      "name": "Dialogue",
      "smoothed": true,
      "type": "TextObject::Text",
      "underlined": false,
      "variables": [],
      "effects": [],
      "behaviors": [],
      "string": "text",
      "font": "",
      "textAlignment": "left",
      "characterSize": 24,
      "color": {
        "b": 255,
        "g": 255,
        "r": 255
      },
      "content": {
        "bold": true,
        "isOutlineEnabled": false,
        "isShadowEnabled": false,
        "italic": false,
        "outlineColor": "255;255;255",
        "outlineThickness": 2,
        "shadowAngle": 90,
        "shadowBlurRadius": 2,
        "shadowColor": "0;0;0",
        "shadowDistance": 4,
        "shadowOpacity": 127,
        "smoothed": true,
        "underlined": false,
        "text": "text",
        "font": "",
        "textAlignment": "left",
        "verticalTextAlignment": "top",
        "characterSize": 24,
        "lineHeight": 0,
        "color": "255;255;255"
      }
    },
    {
      "assetStoreId": "",
      "bold": true,
      "italic": false,
      "name": "options",
      "smoothed": true,
      "type": "TextObject::Text",
      "underlined": false,
      "variables": [],
      "effects": [],
      "behaviors": [],
      "string": "Text",
      "font": "",
      "textAlignment": "left",
      "characterSize": 24,
      "color": {
        "b": 255,
        "g": 255,
        "r": 255
      },
      "content": {
        "bold": true,
        "isOutlineEnabled": false,
        "isShadowEnabled": false,
        "italic": false,
        "outlineColor": "255;255;255",
        "outlineThickness": 2,
        "shadowAngle": 90,
        "shadowBlurRadius": 2,
        "shadowColor": "0;0;0",
        "shadowDistance": 4,
        "shadowOpacity": 127,
        "smoothed": true,
        "underlined": false,
        "text": "Text",
        "font": "",
        "textAlignment": "left",
        "verticalTextAlignment": "top",
        "characterSize": 24,
        "lineHeight": 0,
        "color": "255;255;255"
      }
    },
    {
      "assetStoreId": "",
      "height": 32,
      "name": "black_backdrop",
      "texture": "BlackTile",
      "type": "TiledSpriteObject::TiledSprite",
      "width": 32,
      "variables": [],
      "effects": [],
      "behaviors": []
    },
    {
      "adaptCollisionMaskAutomatically": true,
      "assetStoreId": "",
      "name": "butch",
      "type": "Sprite",
      "updateIfNotVisible": false,
      "variables": [],
      "effects": [],
      "behaviors": [],
      "animations": [
        {
          "name": "NewSprite",
          "useMultipleDirections": false,
          "directions": [
            {
              "looping": false,
              "metadata": "{\"pskl\":{}}",
              "timeBetweenFrames": 0.08,
              "sprites": [
                {
                  "hasCustomCollisionMask": true,
                  "image": "Butch",
                  "points": [],
                  "originPoint": {
                    "name": "origine",
                    "x": 0,
                    "y": 0
                  },
                  "centerPoint": {
                    "automatic": true,
                    "name": "centre",
                    "x": 0,
                    "y": 0
                  },
                  "customCollisionMask": [
                    [
                      {
                        "x": 2,
                        "y": 8
                      },
                      {
                        "x": 62,
                        "y": 8
                      },
                      {
                        "x": 62,
                        "y": 64
                      },
                      {
                        "x": 2,
                        "y": 64
                      }
                    ]
                  ]
                }
              ]
            }
          ]
        }
      ]
    },
    {
      "assetStoreId": "",
      "bold": true,
      "italic": false,
      "name": "secret_butch",
      "smoothed": true,
      "type": "TextObject::Text",
      "underlined": false,
      "variables": [],
      "effects": [],
      "behaviors": [],
      "string": "Frendly woodsmen ",
      "font": "5e2e3fcc57885d5e510934e621be5f8dd7a5b6425cf46ef38073e3d2c3b04048_Kenney Mini.ttf",
      "textAlignment": "left",
      "characterSize": 50,
      "color": {
        "b": 255,
        "g": 255,
        "r": 255
      },
      "content": {
        "bold": true,
        "isOutlineEnabled": false,
        "isShadowEnabled": false,
        "italic": false,
        "outlineColor": "255;255;255",
        "outlineThickness": 2,
        "shadowAngle": 90,
        "shadowBlurRadius": 2,
        "shadowColor": "0;0;0",
        "shadowDistance": 4,
        "shadowOpacity": 127,
        "smoothed": true,
        "underlined": false,
        "text": "Frendly woodsmen ",
        "font": "5e2e3fcc57885d5e510934e621be5f8dd7a5b6425cf46ef38073e3d2c3b04048_Kenney Mini.ttf",
        "textAlignment": "left",
        "verticalTextAlignment": "top",
        "characterSize": 50,
        "lineHeight": 0,
        "color": "255;255;255"
      }
    },
    {
      "assetStoreId": "",
      "height": 32,
      "name": "sky",
      "texture": "BlueTile",
      "type": "TiledSpriteObject::TiledSprite",
      "width": 32,
      "variables": [],
      "effects": [],
      "behaviors": []
    },
    {
      "adaptCollisionMaskAutomatically": true,
      "assetStoreId": "",
      "name": "cloud_",
      "type": "Sprite",
      "updateIfNotVisible": false,
      "variables": [],
      "effects": [],
      "behaviors": [],
      "animations": [
        {
          "name": "NewSprite",
          "useMultipleDirections": false,
          "directions": [
            {
              "looping": false,
              "metadata": "{\"pskl\":{}}",
              "timeBetweenFrames": 0.08,
              "sprites": [
                {
                  "hasCustomCollisionMask": true,
                  "image": "CloudSprite",
                  "points": [],
                  "originPoint": {
                    "name": "origine",
                    "x": 0,
                    "y": 0
                  },
                  "centerPoint": {
                    "automatic": true,
                    "name": "centre",
                    "x": 0,
                    "y": 0
                  },
                  "customCollisionMask": [
                    [
                      {
                        "x": 2,
                        "y": 29
                      },
                      {
                        "x": 62,
                        "y": 29
                      },
                      {
                        "x": 62,
                        "y": 52
                      },
                      {
                        "x": 2,
                        "y": 52
                      }
                    ]
                  ]
                }
              ]
            }
          ]
        }
      ]
    },
    {
      "adaptCollisionMaskAutomatically": true,
      "assetStoreId": "",
      "name": "butch_house_",
      "persistentUuid": "7db4e8c1-1298-4a89-ae8b-2cb7835a58cc",
      "type": "Sprite",
      "updateIfNotVisible": false,
      "variables": [],
      "effects": [],
      "behaviors": [],
      "animations": [
        {
          "name": "NewSprite",
          "useMultipleDirections": false,
          "directions": [
            {
              "looping": false,
              "metadata": "{\"pskl\":{}}",
              "timeBetweenFrames": 0.08,
              "sprites": [
                {
                  "hasCustomCollisionMask": true,
                  "image": "ButchHouse",
                  "points": [],
                  "originPoint": {
                    "name": "origine",
                    "x": 0,
                    "y": 0
                  },
                  "centerPoint": {
                    "automatic": true,
                    "name": "centre",
                    "x": 0,
                    "y": 0
                  },
                  "customCollisionMask": [
                    [
                      {
                        "x": 0,
                        "y": 0
                      },
                      {
                        "x": 64,
                        "y": 0
                      },
                      {
                        "x": 64,
                        "y": 64
                      },
                      {
                        "x": 0,
                        "y": 64
                      }
                    ]
                  ]
                }
              ]
            }
          ]
        }
      ]
    },
    {
      "adaptCollisionMaskAutomatically": true,
      "assetStoreId": "",
      "name": "aaron",
      "type": "Sprite",
      "updateIfNotVisible": false,
      "variables": [],
      "effects": [],
      "behaviors": [],
      "animations": [
        {
          "name": "NewSprite",
          "useMultipleDirections": false,
          "directions": [
            {
              "looping": false,
              "metadata": "{\"pskl\":{}}",
              "timeBetweenFrames": 0.08,
              "sprites": [
                {
                  "hasCustomCollisionMask": true,
                  "image": "Arron",
                  "points": [],
                  "originPoint": {
                    "name": "origine",
                    "x": 0,
                    "y": 0
                  },
                  "centerPoint": {
                    "automatic": true,
                    "name": "centre",
                    "x": 0,
                    "y": 0
                  },
                  "customCollisionMask": [
                    [
                      {
                        "x": 9,
                        "y": 24
                      },
                      {
                        "x": 55,
                        "y": 24
                      },
                      {
                        "x": 55,
                        "y": 64
                      },
                      {
                        "x": 9,
                        "y": 64
                      }
                    ]
                  ]
                }
              ]
            }
          ]
        }
      ]
    },
    {
      "adaptCollisionMaskAutomatically": true,
      "assetStoreId": "",
      "name": "TreeSprite1",
      "persistentUuid": "ea8f513e-ccc8-47fa-b55e-cde203d79162",
      "type": "Sprite",
      "updateIfNotVisible": false,
      "variables": [],
      "effects": [],
      "behaviors": [],
      "animations": [
        {
          "name": "",
          "useMultipleDirections": false,
          "directions": [
            {
              "looping": false,
              "timeBetweenFrames": 0.08,
              "sprites": [
                {
                  "hasCustomCollisionMask": true,
                  "image": "NormalTree2.png",
                  "points": [],
                  "originPoint": {
                    "name": "origine",
                    "x": 0,
                    "y": 0
                  },
                  "centerPoint": {
                    "automatic": true,
                    "name": "centre",
                    "x": 0,
                    "y": 0
                  },
                  "customCollisionMask": [
                    [
                      {
                        "x": 3,
                        "y": 3
                      },
                      {
                        "x": 60,
                        "y": 3
                      },
                      {
                        "x": 60,
                        "y": 59
                      },
                      {
                        "x": 3,
                        "y": 59
                      }
                    ]
                  ]
                }
              ]
            }
          ]
        }
      ]
    },
    {
      "adaptCollisionMaskAutomatically": true,
      "assetStoreId": "",
      "name": "GreenTree",
      "persistentUuid": "e61c216a-b98d-4f9c-8cc1-0a955c6bc3af",
      "type": "Sprite",
      "updateIfNotVisible": false,
      "variables": [],
      "effects": [],
      "behaviors": [],
      "animations": [
        {
          "name": "",
          "useMultipleDirections": false,
          "directions": [
            {
              "looping": false,
              "timeBetweenFrames": 0.08,
              "sprites": [
                {
                  "hasCustomCollisionMask": true,
                  "image": "NeonGreenTree2.png",
                  "points": [],
                  "originPoint": {
                    "name": "origine",
                    "x": 0,
                    "y": 0
                  },
                  "centerPoint": {
                    "automatic": true,
                    "name": "centre",
                    "x": 0,
                    "y": 0
                  },
                  "customCollisionMask": [
                    [
                      {
                        "x": 29,
                        "y": 4
                      },
                      {
                        "x": 98,
                        "y": 4
                      },
                      {
                        "x": 98,
                        "y": 61
                      },
                      {
                        "x": 29,
                        "y": 61
                      }
                    ]
                  ]
                }
              ]
            }
          ]
        }
      ]
    },
    {
      "assetStoreId": "",
      "height": 32,
      "name": "BoundarySprite",
      "persistentUuid": "72d8d364-79f0-41b4-a9a1-1928315f4408",
      "texture": "NewTiledSprite3",
      "type": "TiledSpriteObject::TiledSprite",
      "width": 32,
      "variables": [],
      "effects": [],
      "behaviors": []
    },
    {
      "assetStoreId": "",
      "bold": false,
      "italic": false,
      "name": "NewText",
      "smoothed": true,
      "type": "TextObject::Text",
      "underlined": false,
      "variables": [],
      "effects": [],
      "behaviors": [],
      "string": "Press \"U\" to restart",
      "font": "",
      "textAlignment": "left",
      "characterSize": 20,
      "color": {
        "b": 0,
        "g": 0,
        "r": 0
      },
      "content": {
        "bold": false,
        "isOutlineEnabled": false,
        "isShadowEnabled": false,
        "italic": false,
        "outlineColor": "255;255;255",
        "outlineThickness": 2,
        "shadowAngle": 90,
        "shadowBlurRadius": 2,
        "shadowColor": "0;0;0",
        "shadowDistance": 4,
        "shadowOpacity": 127,
        "smoothed": true,
        "underlined": false,
        "text": "Press \"U\" to restart",
        "font": "",
        "textAlignment": "left",
        "verticalTextAlignment": "top",
        "characterSize": 20,
        "lineHeight": 0,
        "color": "0;0;0"
      }
    },
    {
      "assetStoreId": "5f0df6131c9646dcbe98798196db5b6d806eb25564f86d2e119a084d1e20bf74",
      "name": "BlackDecoratedButton",
      "persistentUuid": "162cf475-8b4f-493f-a8a9-e311c30c8361",
      "type": "PanelSpriteButton::PanelSpriteButton",
      "variant": "Black Decorated Button",
      "variables": [],
      "effects": [],
      "behaviors": [],
      "content": {
        "LeftPadding": 16,
        "RightPadding": 16,
        "PressedLabelOffsetY": 6,
        "BottomPadding": 24,
        "TopPadding": 20,
        "HoveredFadeOutDuration": 0.25,
        "LabelText": "Start game :D"
      }
    }
  ],
  "objectsFolderStructure": {
    "folderName": "__ROOT",
    "children": [
      {
        "objectName": "DontForget"
      },
      {
        "objectName": "SSD"
      },
      {
        "objectName": "grass"
      },
      {
        "objectName": "sky"
      },
      {
        "objectName": "cloud_"
      },
      {
        "objectName": "RockObject"
      },
      {
        "objectName": "TreeObject1"
      },
      {
        "objectName": "path"
      },
      {
        "objectName": "Oliver_Player"
      },
      {
        "objectName": "test"
      },
      {
        "objectName": "stamina_bar"
      },
      {
        "objectName": "stamina_background"
      },
      {
        "objectName": "Dialogue"
      },
      {
        "objectName": "black_backdrop"
      },
      {
        "objectName": "butch"
      },
      {
        "objectName": "secret_butch"
      },
      {
        "objectName": "options"
      },
      {
        "objectName": "butch_house_"
      },
      {
        "objectName": "aaron"
      },
      {
        "objectName": "TreeSprite1"
      },
      {
        "objectName": "BoundarySprite"
      },
      {
        "objectName": "GreenTree"
      },
      {
        "objectName": "NewText"
      },
      {
        "objectName": "BlackDecoratedButton"
      }
    ]
  },
  "events": [
    {
      "type": "BuiltinCommonInstructions::Standard",
      "conditions": [],
      "actions": []
    },
    {
      "type": "BuiltinCommonInstructions::Link",
      "include": {
        "includeConfig": 0
      },
      "target": "branchin type shi"
    },
    {
      "type": "BuiltinCommonInstructions::Link",
      "include": {
        "includeConfig": 0
      },
      "target": "PlayerMovement"
    },
    {
      "type": "BuiltinCommonInstructions::Link",
      "include": {
        "includeConfig": 0
      },
      "target": "Stamina"
    },
    {
      "type": "BuiltinCommonInstructions::Link",
      "include": {
        "includeConfig": 0
      },
      "target": "interactions"
    },
    {
      "type": "BuiltinCommonInstructions::Standard",
      "conditions": [
        {
          "type": {
            "value": "KeyFromTextPressed"
          },
          "parameters": [
            "",
            "\"u\""
          ]
        }
      ],
      "actions": [
        {
          "type": {
            "value": "Delete"
          },
          "parameters": [
            "all",
            ""
          ]
        },
        {
          "type": {
            "value": "BuiltinExternalLayouts::CreateObjectsFromExternalLayout"
          },
          "parameters": [
            "",
            "\"Menu\"",
            "",
            "",
            ""
          ]
        }
      ]
    },
    {
      "type": "BuiltinCommonInstructions::Standard",
      "conditions": [
        {
          "type": {
            "value": "PanelSpriteButton::PanelSpriteButton::IsPressed"
          },
          "parameters": [
            "BlackDecoratedButton",
            ""
          ]
        }
      ],
      "actions": [
        {
          "type": {
            "value": "BuiltinExternalLayouts::CreateObjectsFromExternalLayout"
          },
          "parameters": [
            "",
            "\"level_1\"",
            "",
            "",
            ""
          ]
        }
      ]
    }
  ],
  "layers": [
    {
      "ambientLightColorB": 200,
      "ambientLightColorG": 200,
      "ambientLightColorR": 200,
      "camera2DPlaneMaxDrawingDistance": 5000,
      "camera3DFarPlaneDistance": 10000,
      "camera3DFieldOfView": 45,
      "camera3DNearPlaneDistance": 3,
      "cameraType": "",
      "followBaseLayerCamera": false,
      "isLightingLayer": false,
      "isLocked": false,
      "name": "",
      "renderingType": "",
      "visibility": true,
      "cameras": [
        {
          "defaultSize": true,
          "defaultViewport": true,
          "height": 0,
          "viewportBottom": 1,
          "viewportLeft": 0,
          "viewportRight": 1,
          "viewportTop": 0,
          "width": 0
        }
      ],
      "effects": [
        {
          "effectType": "Scene3D::HemisphereLight",
          "name": "3D Ambient Hemisphere Light",
          "doubleParameters": {
            "elevation": 40,
            "intensity": 0.33,
            "rotation": 300
          },
          "stringParameters": {
            "groundColor": "127;127;127",
            "skyColor": "255;255;255",
            "top": "Z+"
          },
          "booleanParameters": {}
        },
        {
          "effectType": "Scene3D::DirectionalLight",
          "name": "3D Sun Light",
          "doubleParameters": {
            "distanceFromCamera": 1500,
            "elevation": 40,
            "frustumSize": 4000,
            "intensity": 0.75,
            "minimumShadowBias": 0,
            "rotation": 300
          },
          "stringParameters": {
            "color": "255;255;255",
            "shadowQuality": "medium",
            "top": "Z+"
          },
          "booleanParameters": {
            "isCastingShadow": true
          }
        }
      ]
    },
    {
      "ambientLightColorB": 200,
      "ambientLightColorG": 200,
      "ambientLightColorR": 200,
      "camera2DPlaneMaxDrawingDistance": 5000,
      "camera3DFarPlaneDistance": 10000,
      "camera3DFieldOfView": 45,
      "camera3DNearPlaneDistance": 3,
      "cameraType": "",
      "followBaseLayerCamera": false,
      "isLightingLayer": false,
      "isLocked": false,
      "name": "Camera",
      "renderingType": "",
      "visibility": true,
      "cameras": [],
      "effects": [
        {
          "effectType": "Scene3D::HemisphereLight",
          "name": "3D Ambient Hemisphere Light",
          "doubleParameters": {
            "elevation": 40,
            "intensity": 0.33,
            "rotation": 300
          },
          "stringParameters": {
            "groundColor": "127;127;127",
            "skyColor": "255;255;255",
            "top": "Z+"
          },
          "booleanParameters": {}
        },
        {
          "effectType": "Scene3D::DirectionalLight",
          "name": "3D Sun Light",
          "doubleParameters": {
            "distanceFromCamera": 1500,
            "elevation": 40,
            "frustumSize": 4000,
            "intensity": 0.75,
            "minimumShadowBias": 0,
            "rotation": 300
          },
          "stringParameters": {
            "color": "255;255;255",
            "shadowQuality": "medium",
            "top": "Z+"
          },
          "booleanParameters": {
            "isCastingShadow": true
          }
        }
      ]
    },
    {
      "ambientLightColorB": 200,
      "ambientLightColorG": 200,
      "ambientLightColorR": 200,
      "camera2DPlaneMaxDrawingDistance": 5000,
      "camera3DFarPlaneDistance": 10000,
      "camera3DFieldOfView": 45,
      "camera3DNearPlaneDistance": 3,
      "cameraType": "",
      "followBaseLayerCamera": false,
      "isLightingLayer": false,
      "isLocked": false,
      "name": "Ui",
      "renderingType": "",
      "visibility": true,
      "cameras": [],
      "effects": [
        {
          "effectType": "Scene3D::HemisphereLight",
          "name": "3D Ambient Hemisphere Light",
          "doubleParameters": {
            "elevation": 40,
            "intensity": 0.33,
            "rotation": 300
          },
          "stringParameters": {
            "groundColor": "127;127;127",
            "skyColor": "255;255;255",
            "top": "Z+"
          },
          "booleanParameters": {}
        },
        {
          "effectType": "Scene3D::DirectionalLight",
          "name": "3D Sun Light",
          "doubleParameters": {
            "distanceFromCamera": 1500,
            "elevation": 40,
            "frustumSize": 4000,
            "intensity": 0.75,
            "minimumShadowBias": 0,
            "rotation": 300
          },
          "stringParameters": {
            "color": "255;255;255",
            "shadowQuality": "medium",
            "top": "Z+"
          },
          "booleanParameters": {
            "isCastingShadow": true
          }
        }
      ]
    }
  ],
  "behaviorsSharedData": [
    {
      "name": "Animation",
      "type": "AnimatableCapability::AnimatableBehavior"
    },
    {
      "name": "Effect",
      "type": "EffectCapability::EffectBehavior"
    },
    {
      "name": "Flippable",
      "type": "FlippableCapability::FlippableBehavior"
    },
    {
      "name": "Opacity",
      "type": "OpacityCapability::OpacityBehavior"
    },
    {
      "name": "Resizable",
      "type": "ResizableCapability::ResizableBehavior"
    },
    {
      "name": "Scale",
      "type": "ScalableCapability::ScalableBehavior"
    },
    {
      "name": "Text",
      "type": "TextContainerCapability::TextContainerBehavior"
    },
    {
      "name": "TopDownMovement",
      "type": "TopDownMovementBehavior::TopDownMovementBehavior"
    }
  ]
}
